setup.py
dj_authy/__init__.py
dj_authy/admin.py
dj_authy/forms.py
dj_authy/middleware.py
dj_authy/models.py
dj_authy/services.py
dj_authy/signals.py
dj_authy/tests.py
dj_authy/urls.py
dj_authy/views.py
django_authy.egg-info/PKG-INFO
django_authy.egg-info/SOURCES.txt
django_authy.egg-info/dependency_links.txt
django_authy.egg-info/not-zip-safe
django_authy.egg-info/requires.txt
django_authy.egg-info/top_level.txt