Metadata-Version: 1.0
Name: django-authy
Version: 0.1.0
Summary: A Django app for integrating with authy
Home-page: https://github.com/rosscdh/django-authy
Author: Ross Crawford-d'Heureuse
Author-email: ross@lawpal.com
License: MIT
Platform: UNKNOWN
